Workbook

Sheet Assumptions
B1: STARTUP FINANCIAL MODEL — KEY ASSUMPTIONS
B2: All figures in INR
B4: REVENUE ASSUMPTIONS
B5: Year 1 Revenue (INR) | C5: 5400000 | D5: Hardcoded input
B6: Revenue Growth Rate — Y2 | C6: 0.5 | D6: YoY growth
B7: Revenue Growth Rate — Y3 | C7: 0.35 | D7: YoY growth
B8: Revenue Growth Rate — Y4 | C8: 0.25 | D8: YoY growth
B9: Revenue Growth Rate — Y5 | C9: 0.15 | D9: YoY growth
B10: Gross Margin Change | C10: 0.07 | D10: Margin Increase as Scale goes up
B11: Gross Margin % | C11: 0.6 | D11: Product margin
B13: SG&A ASSUMPTIONS
B14: Sales & Marketing (% Revenue) | C14: 0.2 | D14: Scales with rev
B15: General & Admin (% Revenue) | C15: 0.1 | D15: Scales with rev
B16: R&D (% Revenue) | C16: 0.08 | D16: Scales with rev
B18: CAPEX & DEPRECIATION
B19: Capex (% Revenue) | C19: 0.05 | D19: Maintenance + growth
B20: Useful Life (years) | C20: 5 | D20: Straight-line depr.
B21: Beginning PP&E, Net (INR) | C21: 1400000 | D21: Y1 opening balance
B23: DEBT SCHEDULE
B24: Beginning Debt (INR) | C24: 600000 | D24: Seed / Series A debt
B25: Annual Interest Rate | C25: 0.07 | D25: 7% fixed
B26: Annual Debt Repayment (INR) | C26: 100000 | D26: Straight amort.
B28: OTHER
B29: Tax Rate | C29: 0.3 | D29: Marginal Tax Rate in India
B30: Beginning Cash (INR) | C30: 800000 | D30: Cash on hand Y1 start
B31: Beginning Equity (INR) | C31: 2000000 | D31: Paid-in capital

Sheet Income Statement
B1: Income Statement (INR) | K1: Year 3
B2: Metric | C2: Year 1 | D2: Year 2 | E2: Year 3 | F2: Year 4 | G2: Year 5
B3: Revenue | C3: =Assumptions!C5 -> 5400000 | D3: =C3*(1+Assumptions!C6) -> 8100000 | E3: =D3*(1+Assumptions!C7) -> 10935000 | F3: =E3*(1+Assumptions!C8) -> 13668750 | G3: =F3*(1+Assumptions!C9) -> 15719062
B4: Cost of Goods Sold | C4: =-C3*(1-C6) -> -2160000 | D4: =-D3*(1-D6) -> -2899800 | E4: =-E3*(1-E6) -> -3423311.1 | F4: =-F3*(1-F6) -> -3621866.1 | G4: =-G3*(1-G6) -> -3356371.9
B5: Gross Profit | C5: =C3+C4 -> 3240000 | D5: =D3+D4 -> 5200200 | E5: =E3+E4 -> 7511688.9 | F5: =F3+F4 -> 10046884 | G5: =G3+G4 -> 12362691
B6: Gross Margin % | C6: =Assumptions!C11 -> 0.6 | D6: =C6*(1+Assumptions!$C$10) -> 0.642 | E6: =D6*(1+Assumptions!$C$10) -> 0.68694 | F6: =E6*(1+Assumptions!$C$10) -> 0.7350258 | G6: =F6*(1+Assumptions!$C$10) -> 0.78647761
B8: Operating Expenses
B9: Sales & Marketing | C9: =-C3*Assumptions!C14 -> -1080000 | D9: =-D3*Assumptions!C14 -> -1620000 | E9: =-E3*Assumptions!C14 -> -2187000 | F9: =-F3*Assumptions!C14 -> -2733750 | G9: =-G3*Assumptions!C14 -> -3143812.5
B10: General & Administrative | C10: =-C3*Assumptions!C15 -> -540000 | D10: =-D3*Assumptions!C15 -> -810000 | E10: =-E3*Assumptions!C15 -> -1093500 | F10: =-F3*Assumptions!C15 -> -1366875 | G10: =-G3*Assumptions!C15 -> -1571906.2
B11: Research & Development | C11: =-C3*Assumptions!C16 -> -432000 | D11: =-D3*Assumptions!C16 -> -648000 | E11: =-E3*Assumptions!C16 -> -874800 | F11: =-F3*Assumptions!C16 -> -1093500 | G11: =-G3*Assumptions!C16 -> -1257525
B12: Depreciation | C12: =-'Balance Sheet'!C24 -> -354000 | D12: =-'Balance Sheet'!D24 -> -435000 | E12: =-'Balance Sheet'!E24 -> -544350 | F12: =-'Balance Sheet'!F24 -> -681037.5 | G12: =-'Balance Sheet'!G24 -> -838228.12
B13: Total Operating Expenses | C13: =SUM(C9:C12) -> -2406000 | D13: =SUM(D9:D12) -> -3513000 | E13: =SUM(E9:E12) -> -4699650 | F13: =SUM(F9:F12) -> -5875162.5 | G13: =SUM(G9:G12) -> -6811471.9
B15: EBITDA | C15: =C18-C12 -> 1188000 | D15: =D18-D12 -> 2122200 | E15: =E18-E12 -> 3356388.9 | F15: =F18-F12 -> 4852758.9 | G15: =G18-G12 -> 6389446.9
B16: EBITDA Margin | C16: =C15/C3 -> 0.22 | D16: =D15/D3 -> 0.262 | E16: =E15/E3 -> 0.30694 | F16: =F15/F3 -> 0.3550258 | G16: =G15/G3 -> 0.40647761
B18: EBIT (Operating Income) | C18: =C5+C13 -> 834000 | D18: =D5+D13 -> 1687200 | E18: =E5+E13 -> 2812038.9 | F18: =F5+F13 -> 4171721.4 | G18: =G5+G13 -> 5551218.8
B19: Operating Margin | C19: =C18/C3 -> 0.15444444 | D19: =D18/D3 -> 0.2082963 | E19: =E18/E3 -> 0.25715948 | F19: =F18/F3 -> 0.30520138 | G19: =G18/G3 -> 0.35315203
B20: Interest Expense | C20: =-'Debt Schedule'!C6 -> -42000 | D20: =-'Debt Schedule'!D6 -> -35000 | E20: =-'Debt Schedule'!E6 -> -28000 | F20: =-'Debt Schedule'!F6 -> -21000 | G20: =-'Debt Schedule'!G6 -> -14000
B22: EBT (Pre-Tax Income) | C22: =C18+C20 -> 792000 | D22: =D18+D20 -> 1652200 | E22: =E18+E20 -> 2784038.9 | F22: =F18+F20 -> 4150721.4 | G22: =G18+G20 -> 5537218.8
B23: Income Tax Expense | C23: =IF(C22>0,-C22*Assumptions!C29,0) -> -237600 | D23: =IF(D22>0,-D22*Assumptions!C29,0) -> -495660 | E23: =IF(E22>0,-E22*Assumptions!C29,0) -> -835211.67 | F23: =IF(F22>0,-F22*Assumptions!C29,0) -> -1245216.4 | G23: =IF(G22>0,-G22*Assumptions!C29,0) -> -1661165.6
B25: Net Income | C25: =C22+C23 -> 554400 | D25: =D22+D23 -> 1156540 | E25: =E22+E23 -> 1948827.2 | F25: =F22+F23 -> 2905505 | G25: =G22+G23 -> 3876053.1
B26: Net Margin % | C26: =IF(C3=0,0,C25/C3) -> 0.10266667 | D26: =IF(D3=0,0,D25/D3) -> 0.14278272 | E26: =IF(E3=0,0,E25/E3) -> 0.17821923 | F26: =IF(F3=0,0,F25/F3) -> 0.21256552 | G26: =IF(G3=0,0,G25/G3) -> 0.24658297

Sheet Balance Sheet
B1: BALANCE SHEET (INR)
B2: Metric | C2: Year 1 | D2: Year 2 | E2: Year 3 | F2: Year 4 | G2: Year 5
B4: ASSETS
B5: Cash & Equivalents | C5: =C26-C6-C7-C11 -> 1098400 | D5: =D26-D6-D7-D11 -> 1914940 | E5: =E26-E6-E7-E11 -> 3477867.2 | F5: =F26-F6-F7-F11 -> 6007597.2 | G5: =G26-G6-G7-G11 -> 9630894.1
B6: Accounts Receivable | C6: ='Income Statement'!C3*0.1 -> 540000 | D6: ='Income Statement'!D3*0.1 -> 810000 | E6: ='Income Statement'!E3*0.1 -> 1093500 | F6: ='Income Statement'!F3*0.1 -> 1366875 | G6: ='Income Statement'!G3*0.1 -> 1571906.2
B7: Inventory | C7: ='Income Statement'!C3*0.08 -> 432000 | D7: ='Income Statement'!D3*0.08 -> 648000 | E7: ='Income Statement'!E3*0.08 -> 874800 | F7: ='Income Statement'!F3*0.08 -> 1093500 | G7: ='Income Statement'!G3*0.08 -> 1257525
B8: Total Current Assets | C8: =C5+C6+C7 -> 2070400 | D8: =D5+D6+D7 -> 3372940 | E8: =E5+E6+E7 -> 5446167.2 | F8: =F5+F6+F7 -> 8467972.2 | G8: =G5+G6+G7 -> 12460325
B9: PP&E, Gross | C9: ='Capex Schedule'!C6 -> 1770000 | D9: ='Capex Schedule'!D6 -> 2175000 | E9: ='Capex Schedule'!E6 -> 2721750 | F9: ='Capex Schedule'!F6 -> 3405187.5 | G9: ='Capex Schedule'!G6 -> 4191140.6
B10: Accumulated Depreciation | C10: =-'Capex Schedule'!C9 -> -354000 | D10: =-'Capex Schedule'!D9 -> -789000 | E10: =-'Capex Schedule'!E9 -> -1333350 | F10: =-'Capex Schedule'!F9 -> -2014387.5 | G10: =-'Capex Schedule'!G9 -> -2852615.6
B11: PP&E, Net | C11: =C9+C10 -> 1416000 | D11: =D9+D10 -> 1386000 | E11: =E9+E10 -> 1388400 | F11: =F9+F10 -> 1390800 | G11: =G9+G10 -> 1338525
B13: Total Assets | C13: =C8+C11 -> 3486400 | D13: =D8+D11 -> 4758940 | E13: =E8+E11 -> 6834567.2 | F13: =F8+F11 -> 9858772.2 | G13: =G8+G11 -> 13798850
B15: LIABILITIES & EQUITY
B16: Accounts Payable | C16: ='Income Statement'!C3*0.05 -> 270000 | D16: ='Income Statement'!D3*0.05 -> 405000 | E16: ='Income Statement'!E3*0.05 -> 546750 | F16: ='Income Statement'!F3*0.05 -> 683437.5 | G16: ='Income Statement'!G3*0.05 -> 785953.12
B17: Accrued Liabilities | C17: ='Income Statement'!C3*0.03 -> 162000 | D17: ='Income Statement'!D3*0.03 -> 243000 | E17: ='Income Statement'!E3*0.03 -> 328050 | F17: ='Income Statement'!F3*0.03 -> 410062.5 | G17: ='Income Statement'!G3*0.03 -> 471571.87
B18: Total Current Liabilities | C18: =C16+C17 -> 432000 | D18: =D16+D17 -> 648000 | E18: =E16+E17 -> 874800 | F18: =F16+F17 -> 1093500 | G18: =G16+G17 -> 1257525
B19: Long-Term Debt | C19: ='Debt Schedule'!C7 -> 500000 | D19: ='Debt Schedule'!D7 -> 400000 | E19: ='Debt Schedule'!E7 -> 300000 | F19: ='Debt Schedule'!F7 -> 200000 | G19: ='Debt Schedule'!G7 -> 100000
B20: Total Liabilities | C20: =C18+C19 -> 932000 | D20: =D18+D19 -> 1048000 | E20: =E18+E19 -> 1174800 | F20: =F18+F19 -> 1293500 | G20: =G18+G19 -> 1357525
B21: Common Equity / Paid-In Capital | C21: =Assumptions!C31 -> 2000000 | D21: =C21 -> 2000000 | E21: =D21 -> 2000000 | F21: =E21 -> 2000000 | G21: =F21 -> 2000000
B22: Retained Earnings | C22: ='Income Statement'!C25 -> 554400 | D22: =C22+'Income Statement'!D25 -> 1710940 | E22: =D22+'Income Statement'!E25 -> 3659767.2 | F22: =E22+'Income Statement'!F25 -> 6565272.2 | G22: =F22+'Income Statement'!G25 -> 10441325
B23: Total Stockholders' Equity | C23: =C21+C22 -> 2554400 | D23: =D21+D22 -> 3710940 | E23: =E21+E22 -> 5659767.2 | F23: =F21+F22 -> 8565272.2 | G23: =G21+G22 -> 12441325
B24: Depreciation Expense (plug for IS) | C24: ='Capex Schedule'!C8 -> 354000 | D24: ='Capex Schedule'!D8 -> 435000 | E24: ='Capex Schedule'!E8 -> 544350 | F24: ='Capex Schedule'!F8 -> 681037.5 | G24: ='Capex Schedule'!G8 -> 838228.12
B26: TOTAL LIABILITIES & EQUITY | C26: =C20+C23 -> 3486400 | D26: =D20+D23 -> 4758940 | E26: =E20+E23 -> 6834567.2 | F26: =F20+F23 -> 9858772.2 | G26: =G20+G23 -> 13798850
B28: Balance Sheet Check | C28: =C13-C26 -> 0 | D28: =D13-D26 -> 0 | E28: =E13-E26 -> 0 | F28: =F13-F26 -> 0 | G28: =G13-G26 -> 0
B30: Total Liabilities | E30: Total Current Assets

Sheet Cash Flow Statement
B1: CASH FLOW STATEMENT (INR)
B2: Metric | C2: Year 1 | D2: Year 2 | E2: Year 3 | F2: Year 4 | G2: Year 5
B4: Operating Activities
B5: Net Income | C5: ='Income Statement'!C25 -> 554400 | D5: ='Income Statement'!D25 -> 1156540 | E5: ='Income Statement'!E25 -> 1948827.2 | F5: ='Income Statement'!F25 -> 2905505 | G5: ='Income Statement'!G25 -> 3876053.1
B6: Add: Depreciation & Amortization | C6: ='Capex Schedule'!C8 -> 354000 | D6: ='Capex Schedule'!D8 -> 435000 | E6: ='Capex Schedule'!E8 -> 544350 | F6: ='Capex Schedule'!F8 -> 681037.5 | G6: ='Capex Schedule'!G8 -> 838228.12
B7: Change in Accounts Receivable | C7: =-'Balance Sheet'!C6 -> -540000 | D7: =-('Balance Sheet'!D6-'Balance Sheet'!C6) -> -270000 | E7: =-('Balance Sheet'!E6-'Balance Sheet'!D6) -> -283500 | F7: =-('Balance Sheet'!F6-'Balance Sheet'!E6) -> -273375 | G7: =-('Balance Sheet'!G6-'Balance Sheet'!F6) -> -205031.25
B8: Change in Inventory | C8: =-'Balance Sheet'!C7 -> -432000 | D8: =-('Balance Sheet'!D7-'Balance Sheet'!C7) -> -216000 | E8: =-('Balance Sheet'!E7-'Balance Sheet'!D7) -> -226800 | F8: =-('Balance Sheet'!F7-'Balance Sheet'!E7) -> -218700 | G8: =-('Balance Sheet'!G7-'Balance Sheet'!F7) -> -164025
B9: Change in Accounts Payable | C9: ='Balance Sheet'!C16 -> 270000 | D9: ='Balance Sheet'!D16-'Balance Sheet'!C16 -> 135000 | E9: ='Balance Sheet'!E16-'Balance Sheet'!D16 -> 141750 | F9: ='Balance Sheet'!F16-'Balance Sheet'!E16 -> 136687.5 | G9: ='Balance Sheet'!G16-'Balance Sheet'!F16 -> 102515.62
B10: Change in Accrued Liabilities | C10: ='Balance Sheet'!C17 -> 162000 | D10: ='Balance Sheet'!D17-'Balance Sheet'!C17 -> 81000 | E10: ='Balance Sheet'!E17-'Balance Sheet'!D17 -> 85050 | F10: ='Balance Sheet'!F17-'Balance Sheet'!E17 -> 82012.5 | G10: ='Balance Sheet'!G17-'Balance Sheet'!F17 -> 61509.375
B12: Net Cash from Operations | C12: =SUM(C5:C10) -> 368400 | D12: =SUM(D5:D10) -> 1321540 | E12: =SUM(E5:E10) -> 2209677.2 | F12: =SUM(F5:F10) -> 3313167.5 | G12: =SUM(G5:G10) -> 4509250
B14: Investing Activities
B15: Capital Expenditures | C15: =-'Capex Schedule'!C5 -> -270000 | D15: =-'Capex Schedule'!D5 -> -405000 | E15: =-'Capex Schedule'!E5 -> -546750 | F15: =-'Capex Schedule'!F5 -> -683437.5 | G15: =-'Capex Schedule'!G5 -> -785953.12
B17: Net Cash from Investing | C17: =C15 -> -270000 | D17: =D15 -> -405000 | E17: =E15 -> -546750 | F17: =F15 -> -683437.5 | G17: =G15 -> -785953.12
B19: Financing Activities
B20: Debt Repayment | C20: ='Debt Schedule'!C5 -> -100000 | D20: ='Debt Schedule'!D5 -> -100000 | E20: ='Debt Schedule'!E5 -> -100000 | F20: ='Debt Schedule'!F5 -> -100000 | G20: ='Debt Schedule'!G5 -> -100000
B22: Net Cash from Financing | C22: =C20 -> -100000 | D22: =D20 -> -100000 | E22: =E20 -> -100000 | F22: =F20 -> -100000 | G22: =G20 -> -100000
B24: Beginning Cash | C24: =Assumptions!C30 -> 800000 | D24: =C25 -> 798400 | E24: =D25 -> 1614940 | F24: =E25 -> 3177867.2 | G24: =F25 -> 5707597.2
B25: Ending Cash | C25: =C24+C27 -> 798400 | D25: =D24+D27 -> 1614940 | E25: =E24+E27 -> 3177867.2 | F25: =F24+F27 -> 5707597.2 | G25: =G24+G27 -> 9330894.1
B27: Net Change in Cash | C27: =C12+C17+C22 -> -1600 | D27: =D12+D17+D22 -> 816540 | E27: =E12+E17+E22 -> 1562927.2 | F27: =F12+F17+F22 -> 2529730 | G27: =G12+G17+G22 -> 3623296.9

Sheet Capex Schedule
B1: CAPEX & DEPRECIATION SCHEDULE (INR)
B2: Metric | C2: Year 1 | D2: Year 2 | E2: Year 3 | F2: Year 4 | G2: Year 5
B4: Beginning PP&E, Gross | C4: 1500000 | D4: =C6 -> 1770000 | E4: =D6 -> 2175000 | F4: =E6 -> 2721750 | G4: =F6 -> 3405187.5
B5: Capital Expenditures (Additions) | C5: ='Income Statement'!C3*Assumptions!C19 -> 270000 | D5: ='Income Statement'!D3*Assumptions!C19 -> 405000 | E5: ='Income Statement'!E3*Assumptions!C19 -> 546750 | F5: ='Income Statement'!F3*Assumptions!C19 -> 683437.5 | G5: ='Income Statement'!G3*Assumptions!C19 -> 785953.12
B6: Ending PP&E, Gross | C6: =C4+C5 -> 1770000 | D6: =D4+D5 -> 2175000 | E6: =E4+E5 -> 2721750 | F6: =F4+F5 -> 3405187.5 | G6: =G4+G5 -> 4191140.6
B7: Accumulated Depreciation (Beg) | C7: =0 -> 0 | D7: =C9 -> 354000 | E7: =D9 -> 789000 | F7: =E9 -> 1333350 | G7: =F9 -> 2014387.5
B8: Depreciation Expense | C8: =C6/Assumptions!C20 -> 354000 | D8: =D6/Assumptions!C20 -> 435000 | E8: =E6/Assumptions!C20 -> 544350 | F8: =F6/Assumptions!C20 -> 681037.5 | G8: =G6/Assumptions!C20 -> 838228.12
B9: Accumulated Depreciation (End) | C9: =C7+C8 -> 354000 | D9: =D7+D8 -> 789000 | E9: =E7+E8 -> 1333350 | F9: =F7+F8 -> 2014387.5 | G9: =G7+G8 -> 2852615.6
B10: PP&E, Net (Ending) | C10: =C6-C9 -> 1416000 | D10: =D6-D9 -> 1386000 | E10: =E6-E9 -> 1388400 | F10: =F6-F9 -> 1390800 | G10: =G6-G9 -> 1338525

Sheet Debt Schedule
B1: DEBT SCHEDULE (INR)
B2: Metric | C2: Year 1 | D2: Year 2 | E2: Year 3 | F2: Year 4 | G2: Year 5
B4: Beginning Debt Balance | C4: =Assumptions!C24 -> 600000 | D4: =C7 -> 500000 | E4: =D7 -> 400000 | F4: =E7 -> 300000 | G4: =F7 -> 200000
B5: Debt Repayment | C5: =-MIN(Assumptions!C26,C4) -> -100000 | D5: =-MIN(Assumptions!C26,D4) -> -100000 | E5: =-MIN(Assumptions!C26,E4) -> -100000 | F5: =-MIN(Assumptions!C26,F4) -> -100000 | G5: =-MIN(Assumptions!C26,G4) -> -100000
B6: Interest Expense | C6: =C4*Assumptions!C25 -> 42000 | D6: =D4*Assumptions!C25 -> 35000 | E6: =E4*Assumptions!C25 -> 28000 | F6: =F4*Assumptions!C25 -> 21000 | G6: =G4*Assumptions!C25 -> 14000
B7: Ending Debt Balance | C7: =C4+C5 -> 500000 | D7: =D4+D5 -> 400000 | E7: =E4+E5 -> 300000 | F7: =F4+F5 -> 200000 | G7: =G4+G5 -> 100000

Sheet Data_Sheet
B2: Do Not Make Any Changes in this Sheet
B4: Chart Formatting
B6: ='Income Statement'!B2 -> Metric | C6: ='Income Statement'!C2 -> Year 1 | D6: ='Income Statement'!D2 -> Year 2 | E6: ='Income Statement'!E2 -> Year 3 | F6: ='Income Statement'!F2 -> Year 4 | G6: ='Income Statement'!G2 -> Year 5 | I6: Year 1 | J6: 2 | L6: =VLOOKUP('Income Statement'!K1,I6:J10,2,0) -> 4
B7: ='Income Statement'!B9 -> Sales & Marketing | C7: =-'Income Statement'!C9 -> 1080000 | D7: =-'Income Statement'!D9 -> 1620000 | E7: =-'Income Statement'!E9 -> 2187000 | F7: =-'Income Statement'!F9 -> 2733750 | G7: =-'Income Statement'!G9 -> 3143812.5 | I7: Year 2 | J7: 3
B8: ='Income Statement'!B10 -> General & Administrative | C8: =-'Income Statement'!C10 -> 540000 | D8: =-'Income Statement'!D10 -> 810000 | E8: =-'Income Statement'!E10 -> 1093500 | F8: =-'Income Statement'!F10 -> 1366875 | G8: =-'Income Statement'!G10 -> 1571906.2 | I8: Year 3 | J8: 4
B9: ='Income Statement'!B11 -> Research & Development | C9: =-'Income Statement'!C11 -> 432000 | D9: =-'Income Statement'!D11 -> 648000 | E9: =-'Income Statement'!E11 -> 874800 | F9: =-'Income Statement'!F11 -> 1093500 | G9: =-'Income Statement'!G11 -> 1257525 | I9: Year 4 | J9: 5
B10: ='Income Statement'!B12 -> Depreciation | C10: =-'Income Statement'!C12 -> 354000 | D10: =-'Income Statement'!D12 -> 435000 | E10: =-'Income Statement'!E12 -> 544350 | F10: =-'Income Statement'!F12 -> 681037.5 | G10: =-'Income Statement'!G12 -> 838228.12 | I10: Year 5 | J10: 6
B12: =B7 -> Sales & Marketing | C12: =C7/SUM(C$7:C$10) -> 0.44887781 | D12: =D7/SUM(D$7:D$10) -> 0.46114432 | E12: =E7/SUM(E$7:E$10) -> 0.4653538 | F12: =F7/SUM(F$7:F$10) -> 0.46530628 | G12: =G7/SUM(G$7:G$10) -> 0.46154672 | I12: =B12 -> Sales & Marketing | J12: =VLOOKUP(I12,$B$7:$G$10,$L$6,0) -> 2187000
B13: =B8 -> General & Administrative | C13: =C8/SUM(C$7:C$10) -> 0.2244389 | D13: =D8/SUM(D$7:D$10) -> 0.23057216 | E13: =E8/SUM(E$7:E$10) -> 0.2326769 | F13: =F8/SUM(F$7:F$10) -> 0.23265314 | G13: =G8/SUM(G$7:G$10) -> 0.23077336 | I13: =B13 -> General & Administrative | J13: =VLOOKUP(I13,$B$7:$G$10,$L$6,0) -> 1093500
B14: =B9 -> Research & Development | C14: =C9/SUM(C$7:C$10) -> 0.17955112 | D14: =D9/SUM(D$7:D$10) -> 0.18445773 | E14: =E9/SUM(E$7:E$10) -> 0.18614152 | F14: =F9/SUM(F$7:F$10) -> 0.18612251 | G14: =G9/SUM(G$7:G$10) -> 0.18461869 | I14: =B14 -> Research & Development | J14: =VLOOKUP(I14,$B$7:$G$10,$L$6,0) -> 874800
B15: =B10 -> Depreciation | C15: =C10/SUM(C$7:C$10) -> 0.14713217 | D15: =D10/SUM(D$7:D$10) -> 0.12382579 | E15: =E10/SUM(E$7:E$10) -> 0.11582777 | F15: =F10/SUM(F$7:F$10) -> 0.11591807 | G15: =G10/SUM(G$7:G$10) -> 0.12306123 | I15: =B15 -> Depreciation | J15: =VLOOKUP(I15,$B$7:$G$10,$L$6,0) -> 544350
B17: Chart of Balance Sheet
B18: Assets
B19: ='Balance Sheet'!E30 -> Total Current Assets | C19: =VLOOKUP('Balance Sheet'!$E$30,'Balance Sheet'!$B$2:$G$26,2,0) -> 2070400 | D19: =VLOOKUP('Balance Sheet'!$E$30,'Balance Sheet'!$B$2:$G$26,3,0) -> 3372940 | E19: =VLOOKUP('Balance Sheet'!$E$30,'Balance Sheet'!$B$2:$G$26,4,0) -> 5446167.2 | F19: =VLOOKUP('Balance Sheet'!$E$30,'Balance Sheet'!$B$2:$G$26,5,0) -> 8467972.2 | G19: =VLOOKUP('Balance Sheet'!$E$30,'Balance Sheet'!$B$2:$G$26,6,0) -> 12460325
B20: Liabilities
B21: ='Balance Sheet'!B30 -> Total Liabilities | C21: =VLOOKUP('Balance Sheet'!$B$30,'Balance Sheet'!$B$2:$G$26,2,0) -> 932000 | D21: =VLOOKUP('Balance Sheet'!$B$30,'Balance Sheet'!$B$2:$G$26,3,0) -> 1048000 | E21: =VLOOKUP('Balance Sheet'!$B$30,'Balance Sheet'!$B$2:$G$26,4,0) -> 1174800 | F21: =VLOOKUP('Balance Sheet'!$B$30,'Balance Sheet'!$B$2:$G$26,5,0) -> 1293500 | G21: =VLOOKUP('Balance Sheet'!$B$30,'Balance Sheet'!$B$2:$G$26,6,0) -> 1357525
